datapi/__init__.py
datapi/api_client.py
datapi/catalogue.py
datapi/config.py
datapi/legacy_api_client.py
datapi/processing.py
datapi/profile.py
datapi/py.typed
datapi/version.py
datapi-0.3.0.dist-info/LICENSE
datapi-0.3.0.dist-info/METADATA
datapi-0.3.0.dist-info/WHEEL
datapi-0.3.0.dist-info/top_level.txt
datapi-0.3.0.dist-info/RECORD
