Metadata-Version: 2.2
Name: datapi
Version: 0.3.0
Summary: ESEE Data Stores API Python Client
License:                                  Apache License
Project-URL: documentation, https://ecmwf-projects.github.io/datapi/
Project-URL: source, https://github.com/ecmwf-projects/datapi
Project-URL: tracker, https://github.com/ecmwf-projects/datapi/issues
Classifier: Development Status :: 2 - Pre-Alpha
Classifier: Intended Audience :: Science/Research
Classifier: License :: OSI Approved :: Apache Software License
Classifier: Operating System :: OS Independent
Classifier: Programming Language :: Python
Classifier: Programming Language :: Python :: 3
Classifier: Programming Language :: Python :: 3.8
Classifier: Programming Language :: Python :: 3.9
Classifier: Programming Language :: Python :: 3.10
Classifier: Programming Language :: Python :: 3.11
Classifier: Programming Language :: Python :: 3.12
Classifier: Programming Language :: Python :: 3.13
Classifier: Topic :: Scientific/Engineering
Requires-Python: >=3.8
License-File: LICENSE
Requires-Dist: attrs
Requires-Dist: multiurl>=0.3.2
Requires-Dist: requests
Requires-Dist: typing-extensions
Provides-Extra: legacy
Requires-Dist: cdsapi>=0.7.5; extra == "legacy"
